src/__init__.py
src/htesth.py
src/main.py
tests/__init__.py
tests/test_htesth.py
htesth-0.0.10.dist-info/LICENSE.txt
htesth-0.0.10.dist-info/METADATA
htesth-0.0.10.dist-info/WHEEL
htesth-0.0.10.dist-info/top_level.txt
htesth-0.0.10.dist-info/RECORD
