Metadata-Version: 2.1
Name: htesth
Version: 0.0.10
Summary: This is a test package
Author: melong
Requires-Python: ~=3.6
License-File: LICENSE.txt
